Workbook

Sheet Fact_Transactions
A1: Transaction ID | B1: Order ID | C1: Order Date | D1: Product ID | E1: Region ID | F1: Quantity | G1: Unit Price | H1: Discount | I1: Sales | J1: Cost | K1: Profit | L1: Profit Margin | M1: Payment Method | N1: Order Status | O1: Customer ID | P1: Customer_Name | Q1: Product_Name | R1: Region_Name
A2: TRX03211 | B2: ORD1001 | C2: 45785.604 | D2: PROD116 | E2: REG009 | F2: 4 | G2: 110000 | H2: 0 | I2: Rp440,000.00 | J2: Rp288,000.00 | K2: Rp152,000.00 | L2: 0.3455 | M2: Cash | N2: Completed | O2: CUST0246 | P2: {=_xlfn.XLOOKUP(O2, Dim_Customer_Master!A:A, Dim_Customer_Master!B:B, "Unknown Customer")} -> Nanda Susanto | Q2: {=_xlfn.XLOOKUP(D2, Dim_Product_Master!A:A, Dim_Product_Master!B:B, "")} -> Logitech Case Keyboard | R2: {=_xlfn.XLOOKUP(E2, Dim_Region!A:A, Dim_Region!B:B, "")} -> Bengkulu
A3: TRX03468 | B3: ORD1001 | C3: 45785.604 | D3: PROD107 | E3: REG009 | F3: 8 | G3: 4094000 | H3: 0.15 | I3: Rp27,839,200.00 | J3: Rp24,704,000.00 | K3: Rp3,135,200.00 | L3: 0.1126 | M3: Cash | N3: Completed | O3: CUST0246 | P3: {=_xlfn.XLOOKUP(O3, Dim_Customer_Master!A:A, Dim_Customer_Master!B:B, "Unknown Customer")} -> Nanda Susanto | Q3: {=_xlfn.XLOOKUP(D3, Dim_Product_Master!A:A, Dim_Product_Master!B:B, "")} -> Ligna Meja Sudut | R3: {=_xlfn.XLOOKUP(E3, Dim_Region!A:A, Dim_Region!B:B, "")} -> Bengkulu
A4: TRX00226 | B4: ORD1003 | C4: 44960.726 | D4: PROD062 | E4: REG007 | F4: 10 | G4: 21000 | H4: 0.1 | I4: Rp189,000.00 | J4: Rp150,000.00 | K4: Rp39,000.00 | L4: 0.2063 | M4: QRIS | N4: Completed | O4: CUST0200 | P4: {=_xlfn.XLOOKUP(O4, Dim_Customer_Master!A:A, Dim_Customer_Master!B:B, "Unknown Customer")} -> Hariyanto Saputra | Q4: {=_xlfn.XLOOKUP(D4, Dim_Product_Master!A:A, Dim_Product_Master!B:B, "")} -> Kenko Kalkulator Kantor | R4: {=_xlfn.XLOOKUP(E4, Dim_Region!A:A, Dim_Region!B:B, "")} -> Sumatera Selatan
A5: TRX01520 | B5: ORD1003 | C5: 44960.726 | D5: PROD105 | E5: REG007 | F5: 12 | G5: 672000 | H5: 0.2 | I5: Rp6,451,200.00 | J5: Rp6,936,000.00 | K5: -Rp484,800.00 | L5: -0.0751 | M5: QRIS | N5: Completed | O5: CUST0200 | P5: {=_xlfn.XLOOKUP(O5, Dim_Customer_Master!A:A, Dim_Customer_Master!B:B, "Unknown Customer")} -> Hariyanto Saputra | Q5: {=_xlfn.XLOOKUP(D5, Dim_Product_Master!A:A, Dim_Product_Master!B:B, "")} -> Epson Hard Disk Eksternal 1TB | R5: {=_xlfn.XLOOKUP(E5, Dim_Region!A:A, Dim_Region!B:B, "")} -> Sumatera Selatan
A6: TRX00877 | B6: ORD1007 | C6: 44933.689 | D6: PROD107 | E6: REG020 | F6: 8 | G6: 4113000 | H6: 0.05 | I6: Rp31,258,800.00 | J6: Rp24,704,000.00 | K6: Rp6,554,800.00 | L6: 0.2097 | M6: VA | N6: Completed | O6: CUST0440 | P6: {=_xlfn.XLOOKUP(O6, Dim_Customer_Master!A:A, Dim_Customer_Master!B:B, "Unknown Customer")} -> Eko Pratiwi | Q6: {=_xlfn.XLOOKUP(D6, Dim_Product_Master!A:A, Dim_Product_Master!B:B, "")} -> Ligna Meja Sudut | R6: {=_xlfn.XLOOKUP(E6, Dim_Region!A:A, Dim_Region!B:B, "")} -> Kalimantan Barat
A7: TRX01151 | B7: ORD1007 | C7: 44933.689 | D7: PROD015 | E7: REG020 | F7: 5 | G7: 93500 | H7: 0.2 | I7: Rp374,000.00 | J7: Rp360,000.00 | K7: Rp14,000.00 | L7: 0.0374 | M7: VA | N7: Completed | O7: CUST0440 | P7: {=_xlfn.XLOOKUP(O7, Dim_Customer_Master!A:A, Dim_Customer_Master!B:B, "Unknown Customer")} -> Eko Pratiwi | Q7: {=_xlfn.XLOOKUP(D7, Dim_Product_Master!A:A, Dim_Product_Master!B:B, "")} -> Kenmaster Ember Plastik Besar | R7: {=_xlfn.XLOOKUP(E7, Dim_Region!A:A, Dim_Region!B:B, "")} -> Kalimantan Barat
A8: TRX03626 | B8: ORD1007 | C8: 44933.689 | D8: PROD016 | E8: REG020 | F8: 10 | G8: 474500 | H8: 0.05 | I8: Rp4,507,750.00 | J8: Rp3,010,000.00 | K8: Rp1,497,750.00 | L8: 0.3323 | M8: VA | N8: Completed | O8: CUST0440 | P8: {=_xlfn.XLOOKUP(O8, Dim_Customer_Master!A:A, Dim_Customer_Master!B:B, "Unknown Customer")} -> Eko Pratiwi | Q8: {=_xlfn.XLOOKUP(D8, Dim_Product_Master!A:A, Dim_Product_Master!B:B, "")} -> Technoplast Rak Serbaguna Besi | R8: {=_xlfn.XLOOKUP(E8, Dim_Region!A:A, Dim_Region!B:B, "")} -> Kalimantan Barat
A9: TRX04757 | B9: ORD1007 | C9: 44933.689 | D9: PROD028 | E9: REG020 | F9: 2 | G9: 583000 | H9: 0.2 | I9: Rp932,800.00 | J9: Rp892,000.00 | K9: Rp40,800.00 | L9: 0.0437 | M9: VA | N9: Completed | O9: CUST0440 | P9: {=_xlfn.XLOOKUP(O9, Dim_Customer_Master!A:A, Dim_Customer_Master!B:B, "Unknown Customer")} -> Eko Pratiwi | Q9: {=_xlfn.XLOOKUP(D9, Dim_Product_Master!A:A, Dim_Product_Master!B:B, "")} -> Sanken LED TV 50 Inch | R9: {=_xlfn.XLOOKUP(E9, Dim_Region!A:A, Dim_Region!B:B, "")} -> Kalimantan Barat
A10: TRX00350 | B10: ORD1008 | C10: 45044.61 | D10: PROD096 | E10: REG025 | F10: 12 | G10: 1163500 | H10: 0.2 | I10: Rp11,169,600.00 | J10: Rp9,600,000.00 | K10: Rp1,569,600.00 | L10: 0.1405 | M10: QRIS | N10: Pending | O10: CUST0233 | P10: {=_xlfn.XLOOKUP(O10, Dim_Customer_Master!A:A, Dim_Customer_Master!B:B, "Unknown Customer")} -> Rizky Wulandari | Q10: {=_xlfn.XLOOKUP(D10, Dim_Product_Master!A:A, Dim_Product_Master!B:B, "")} -> Sharp Microwave 20L | R10: {=_xlfn.XLOOKUP(E10, Dim_Region!A:A, Dim_Region!B:B, "")} -> Sulawesi Utara
A11: TRX00429 | B11: ORD1008 | C11: 45044.61 | D11: PROD077 | E11: REG025 | F11: 6 | G11: 1716500 | H11: 0.05 | I11: Rp9,784,050.00 | J11: Rp7,068,000.00 | K11: Rp2,716,050.00 | L11: 0.2776 | M11: QRIS | N11: Pending | O11: CUST0233 | P11: {=_xlfn.XLOOKUP(O11, Dim_Customer_Master!A:A, Dim_Customer_Master!B:B, "Unknown Customer")} -> Rizky Wulandari | Q11: {=_xlfn.XLOOKUP(D11, Dim_Product_Master!A:A, Dim_Product_Master!B:B, "")} -> Chitose Kursi Kantor Manager | R11: {=_xlfn.XLOOKUP(E11, Dim_Region!A:A, Dim_Region!B:B, "")} -> Sulawesi Utara
A12: TRX03654 | B12: ORD1008 | C12: 45044.61 | D12: PROD056 | E12: REG025 | F12: 3 | G12: 8807000 | H12: 0.05 | I12: Rp25,099,950.00 | J12: Rp21,501,000.00 | K12: Rp3,598,950.00 | L12: 0.1434 | M12: QRIS | N12: Pending | O12: CUST0233 | P12: {=_xlfn.XLOOKUP(O12, Dim_Customer_Master!A:A, Dim_Customer_Master!B:B, "Unknown Customer")} -> Rizky Wulandari | Q12: {=_xlfn.XLOOKUP(D12, Dim_Product_Master!A:A, Dim_Product_Master!B:B, "")} -> Acer Smartphone Android | R12: {=_xlfn.XLOOKUP(E12, Dim_Region!A:A, Dim_Region!B:B, "")} -> Sulawesi Utara
A13: TRX00196 | B13: ORD1009 | C13: 45077.79 | D13: PROD005 | E13: REG034 | F13: 12 | G13: 5082500 | H13: 0.05 | I13: Rp57,940,500.00 | J13: Rp42,708,000.00 | K13: Rp15,232,500.00 | L13: 0.2629 | M13: QRIS | N13: Completed | O13: CUST0157 | P13: {=_xlfn.XLOOKUP(O13, Dim_Customer_Master!A:A, Dim_Customer_Master!B:B, "Unknown Customer")} -> Tia Nasution | Q13: {=_xlfn.XLOOKUP(D13, Dim_Product_Master!A:A, Dim_Product_Master!B:B, "")} -> LG Air Fryer 4L | R13: {=_xlfn.XLOOKUP(E13, Dim_Region!A:A, Dim_Region!B:B, "")} -> Papua
... A4959: TRX04501 | B4959: ORD3200 | C4959: 45215.874 | D4959: PROD060 | E4959: REG026 | F4959: 10 | G4959: 715500 | H4959: 0.2 | I4959: Rp5,724,000.00 | J4959: Rp4,850,000.00 | K4959: Rp874,000.00 | L4959: 0.1527 | M4959: Transfer | N4959: Completed | O4959: CUST0129 | P4959: {=_xlfn.XLOOKUP(O4959, Dim_Customer_Master!A:A, Dim_Customer_Master!B:B, "Unknown Customer")} -> Candra Wibisono | Q4959: {=_xlfn.XLOOKUP(D4959, Dim_Product_Master!A:A, Dim_Product_Master!B:B, "")} -> Napolly Keranjang Serbaguna | R4959: {=_xlfn.XLOOKUP(E4959, Dim_Region!A:A, Dim_Region!B:B, "")} -> Sulawesi Tengah

Sheet Fact_Transactions_Clean
A1: Transaction ID | B1: Order ID | C1: Order Date | D1: Customer ID | E1: Product ID | F1: Region ID | G1: Quantity | H1: Unit Price | I1: Discount | J1: Sales | K1: Cost | L1: Profit | M1: Profit Margin | N1: Payment Method | O1: Order Status | P1: Customer_Name | Q1: Product_Name | R1: Region_Name
A2: TRX03211 | B2: ORD1001 | C2: 45785.604 | D2: CUST0246 | E2: PROD116 | F2: REG009 | G2: 4 | H2: 110000 | I2: 0 | J2: Rp440,000.00 | K2: Rp288,000.00 | L2: Rp152,000.00 | M2: 0.3455 | N2: Cash | O2: Completed | P2: Nanda Susanto | Q2: Logitech Case Keyboard | R2: Bengkulu
A3: TRX03468 | B3: ORD1001 | C3: 45785.604 | D3: CUST0246 | E3: PROD107 | F3: REG009 | G3: 8 | H3: 4094000 | I3: 0.15 | J3: Rp27,839,200.00 | K3: Rp24,704,000.00 | L3: Rp3,135,200.00 | M3: 0.1126 | N3: Cash | O3: Completed | P3: Nanda Susanto | Q3: Ligna Meja Sudut | R3: Bengkulu
A4: TRX00226 | B4: ORD1003 | C4: 44960.726 | D4: CUST0200 | E4: PROD062 | F4: REG007 | G4: 10 | H4: 21000 | I4: 0.1 | J4: Rp189,000.00 | K4: Rp150,000.00 | L4: Rp39,000.00 | M4: 0.2063 | N4: QRIS | O4: Completed | P4: Hariyanto Saputra | Q4: Kenko Kalkulator Kantor | R4: Sumatera Selatan
A5: TRX01520 | B5: ORD1003 | C5: 44960.726 | D5: CUST0200 | E5: PROD105 | F5: REG007 | G5: 12 | H5: 672000 | I5: 0.2 | J5: Rp6,451,200.00 | K5: Rp6,936,000.00 | L5: -Rp484,800.00 | M5: -0.0751 | N5: QRIS | O5: Completed | P5: Hariyanto Saputra | Q5: Epson Hard Disk Eksternal 1TB | R5: Sumatera Selatan
A6: TRX00877 | B6: ORD1007 | C6: 44933.689 | D6: CUST0440 | E6: PROD107 | F6: REG020 | G6: 8 | H6: 4113000 | I6: 0.05 | J6: Rp31,258,800.00 | K6: Rp24,704,000.00 | L6: Rp6,554,800.00 | M6: 0.2097 | N6: VA | O6: Completed | P6: Eko Pratiwi | Q6: Ligna Meja Sudut | R6: Kalimantan Barat
A7: TRX01151 | B7: ORD1007 | C7: 44933.689 | D7: CUST0440 | E7: PROD015 | F7: REG020 | G7: 5 | H7: 93500 | I7: 0.2 | J7: Rp374,000.00 | K7: Rp360,000.00 | L7: Rp14,000.00 | M7: 0.0374 | N7: VA | O7: Completed | P7: Eko Pratiwi | Q7: Kenmaster Ember Plastik Besar | R7: Kalimantan Barat
A8: TRX03626 | B8: ORD1007 | C8: 44933.689 | D8: CUST0440 | E8: PROD016 | F8: REG020 | G8: 10 | H8: 474500 | I8: 0.05 | J8: Rp4,507,750.00 | K8: Rp3,010,000.00 | L8: Rp1,497,750.00 | M8: 0.3323 | N8: VA | O8: Completed | P8: Eko Pratiwi | Q8: Technoplast Rak Serbaguna Besi | R8: Kalimantan Barat
A9: TRX04757 | B9: ORD1007 | C9: 44933.689 | D9: CUST0440 | E9: PROD028 | F9: REG020 | G9: 2 | H9: 583000 | I9: 0.2 | J9: Rp932,800.00 | K9: Rp892,000.00 | L9: Rp40,800.00 | M9: 0.0437 | N9: VA | O9: Completed | P9: Eko Pratiwi | Q9: Sanken LED TV 50 Inch | R9: Kalimantan Barat
A10: TRX00350 | B10: ORD1008 | C10: 45044.61 | D10: CUST0233 | E10: PROD096 | F10: REG025 | G10: 12 | H10: 1163500 | I10: 0.2 | J10: Rp11,169,600.00 | K10: Rp9,600,000.00 | L10: Rp1,569,600.00 | M10: 0.1405 | N10: QRIS | O10: Pending | P10: Rizky Wulandari | Q10: Sharp Microwave 20L | R10: Sulawesi Utara
A11: TRX00429 | B11: ORD1008 | C11: 45044.61 | D11: CUST0233 | E11: PROD077 | F11: REG025 | G11: 6 | H11: 1716500 | I11: 0.05 | J11: Rp9,784,050.00 | K11: Rp7,068,000.00 | L11: Rp2,716,050.00 | M11: 0.2776 | N11: QRIS | O11: Pending | P11: Rizky Wulandari | Q11: Chitose Kursi Kantor Manager | R11: Sulawesi Utara
A12: TRX03654 | B12: ORD1008 | C12: 45044.61 | D12: CUST0233 | E12: PROD056 | F12: REG025 | G12: 3 | H12: 8807000 | I12: 0.05 | J12: Rp25,099,950.00 | K12: Rp21,501,000.00 | L12: Rp3,598,950.00 | M12: 0.1434 | N12: QRIS | O12: Pending | P12: Rizky Wulandari | Q12: Acer Smartphone Android | R12: Sulawesi Utara
A13: TRX00196 | B13: ORD1009 | C13: 45077.79 | D13: CUST0157 | E13: PROD005 | F13: REG034 | G13: 12 | H13: 5082500 | I13: 0.05 | J13: Rp57,940,500.00 | K13: Rp42,708,000.00 | L13: Rp15,232,500.00 | M13: 0.2629 | N13: QRIS | O13: Completed | P13: Tia Nasution | Q13: LG Air Fryer 4L | R13: Papua
... A4959: TRX04501 | B4959: ORD3200 | C4959: 45215.874 | D4959: CUST0129 | E4959: PROD060 | F4959: REG026 | G4959: 10 | H4959: 715500 | I4959: 0.2 | J4959: Rp5,724,000.00 | K4959: Rp4,850,000.00 | L4959: Rp874,000.00 | M4959: 0.1527 | N4959: Transfer | O4959: Completed | P4959: Candra Wibisono | Q4959: Napolly Keranjang Serbaguna | R4959: Sulawesi Tengah

Sheet Dim_Customer_Master
A1: Customer ID | B1: Customer Name | C1: Gender | D1: Age | E1: Customer Segment | F1: Province | G1: Region | H1: City | I1: Join Date | J1: Loyalty
A2: CUST0001 | B2: Panji Saputra | C2: Male | D2: 44 | E2: Consumer | F2: Aceh | G2: Sumatera | H2: Lhokseumawe | I2: 44397 | J2: Platinum
A3: CUST0002 | B3: Maya Astuti | C3: Female | D3: 26 | E3: Government | F3: Banten | G3: Jawa | H3: Tangerang | I3: 44213 | J3: Bronze
A4: CUST0003 | B4: Ani Wibowo | C4: Female | D4: 60 | E4: Small Business | F4: Bengkulu | G4: Sumatera | H4: Bengkulu | I4: 44770 | J4: Gold
A5: CUST0004 | B5: Novi Simatupang | C5: Female | D5: 28 | E5: Government | F5: Jawa Barat | G5: Jawa | H5: Depok | I5: 45526 | J5: Bronze
A6: CUST0005 | B6: Salsabila Susanto | C6: Female | D6: 28 | E6: Small Business | F6: Banten | G6: Jawa | H6: Tangerang Selatan | I6: 44348 | J6: Bronze
A7: CUST0006 | B7: Taufik Hidayat | C7: Male | D7: 20 | E7: Government | F7: Riau | G7: Sumatera | H7: Pekanbaru | I7: 44689 | J7: Platinum
A8: CUST0007 | B8: Malik Permata | C8: Male | D8: 49 | E8: Corporate | F8: Kalimantan Barat | G8: Kalimantan | H8: Singkawang | I8: 44716 | J8: Bronze
A9: CUST0008 | B9: Hendra Sitompul | C9: Male | D9: 68 | E9: Government | F9: DKI Jakarta | G9: Jawa | H9: Jakarta Utara | I9: 45542 | J9: Bronze
A10: CUST0009 | B10: Olivia Pratama | C10: Female | D10: 52 | E10: Government | F10: Sumatera Utara | G10: Sumatera | H10: Medan | I10: 44901 | J10: Silver
A11: CUST0010 | B11: Kurniawan Hidayat | C11: Male | D11: 48 | E11: Government | F11: Jawa Barat | G11: Jawa | H11: Depok | I11: 44924 | J11: Platinum
A12: CUST0013 | B12: Novi Sitompul | C12: Female | D12: 45 | E12: Corporate | F12: Bengkulu | G12: Sumatera | H12: Bengkulu | I12: 45506 | J12: Bronze
A13: CUST0014 | B13: Surya Simanjuntak | C13: Male | D13: 25 | E13: Consumer | F13: Lampung | G13: Sumatera | H13: Bandar Lampung | I13: 45689 | J13: Platinum
... A518: CUST0543 | B518: Oktavia Tampubolon | C518: Female | D518: 48 | E518: Government | F518: Sumatera Utara | G518: Sumatera | H518: Binjai | I518: 45637 | J518: Bronze

Sheet Dim_Product_Master
A1: Product ID | B1: Product Name | C1: Category | D1: Sub Category | E1: Brand | F1: Standard Cost | G1: Selling Price | H1: Launch Date | I1: Status
A2: PROD001 | B2: Samsung AC Split 1 PK | C2: Electronics | D2: Peralatan Dapur | E2: Samsung | F2: 4091000 | G2: 6382000 | H2: 44708 | I2: Active
A3: PROD002 | B3: Diva Kursi Kantor Manager | C3: Furniture | D3: Furnitur Kantor | E3: Diva | F3: 2965000 | G3: 4079000 | H3: 44582 | I3: Active
A4: PROD003 | B4: Rich Home Filing Cabinet | C4: Furniture | D4: Furnitur Rumah Tangga | E4: Rich Home | F4: 506000 | G4: 662000 | H4: 44802 | I4: Active
A5: PROD004 | B5: Robot Mousepad Gaming | C5: Accessories | D5: Aksesori Handphone | E5: Robot | F5: 120000 | G5: 193000 | H5: 45160 | I5: Active
A6: PROD005 | B6: LG Air Fryer 4L | C6: Electronics | D6: TV & Audio Video | E6: LG | F6: 3559000 | G6: 5399000 | H6: 45527 | I6: Active
A7: PROD006 | B7: Boxy Correction Tape | C7: Office Supplies | D7: Kertas & Percetakan | E7: Boxy | F7: 95000 | G7: 143000 | H7: 45465 | I7: Active
A8: PROD007 | B8: Deli Gunting Kantor | C8: Office Supplies | D8: Kertas & Percetakan | E8: Deli | F8: 76000 | G8: 98000 | H8: 45407 | I8: Active
A9: PROD008 | B9: Sanyo Rice Cooker 1.8L | C9: Electronics | D9: Pendingin & Tata Udara | E9: Sanyo | F9: 596000 | G9: 933000 | H9: 45370 | I9: Active
A10: PROD009 | B10: Lion Star Rak Susun Besi | C10: Storage | D10: Rak & Lemari Penyimpanan | E10: Lion Star | F10: 303000 | G10: 435000 | H10: 45550 | I10: Active
A11: PROD010 | B11: Technoplast Kotak Perkakas | C11: Storage | D11: Wadah & Kontainer | E11: Technoplast | F11: 77000 | G11: 108000 | H11: 44938 | I11: Active
A12: PROD011 | B12: Faber-Castell Tinta Printer Refill | C12: Office Supplies | D12: Alat Tulis Kantor | E12: Faber-Castell | F12: 63000 | G12: 88000 | H12: 45758 | I12: Active
A13: PROD012 | B13: Sanken Setrika Uap | C13: Electronics | D13: Pendingin & Tata Udara | E13: Sanken | F13: 1827000 | G13: 2412000 | H13: 44736 | I13: Active
... A123: PROD122 | B123: Cosmos Kulkas 2 Pintu | C123: Electronics | D123: Pendingin & Tata Udara | E123: Cosmos | F123: 5459000 | G123: 7145000 | H123: 45165 | I123: Active

Sheet Dim_Region
A1: Region ID | B1: Province | C1: Region
A2: REG001 | B2: Aceh | C2: Sumatera
A3: REG002 | B3: Sumatera Utara | C3: Sumatera
A4: REG003 | B4: Sumatera Barat | C4: Sumatera
A5: REG004 | B5: Riau | C5: Sumatera
A6: REG005 | B6: Kepulauan Riau | C6: Sumatera
A7: REG006 | B7: Jambi | C7: Sumatera
A8: REG007 | B8: Sumatera Selatan | C8: Sumatera
A9: REG008 | B9: Kepulauan Bangka Belitung | C9: Sumatera
A10: REG009 | B10: Bengkulu | C10: Sumatera
A11: REG010 | B11: Lampung | C11: Sumatera
A12: REG011 | B12: DKI Jakarta | C12: Jawa
... A35: REG034 | B35: Papua | C35: Maluku & Papua
